LICENSE
MANIFEST.in
README.md
requirements.txt
setup.cfg
setup.py
modvis/ATSutils.py
modvis/__init__.py
modvis/ats_xdmf.py
modvis/ats_xml.py
modvis/colors.py
modvis/general_plots.py
modvis/mesh_interpretation.py
modvis/modvis.py
modvis/objectivefunctions.py
modvis/plot_vis_file.py
modvis/transect_data.py
modvis/utils.py
modvis.egg-info/PKG-INFO
modvis.egg-info/SOURCES.txt
modvis.egg-info/dependency_links.txt
modvis.egg-info/not-zip-safe
modvis.egg-info/requires.txt
modvis.egg-info/top_level.txt
tests/test_modvis.py