Metadata-Version: 2.1
Name: modvis
Version: 0.0.9
Summary: A python package for model visualization.
Home-page: https://github.com/pinshuai/modvis
Author: Pin Shuai
Author-email: pin.shuai@usu.edu
License: MIT license
Keywords: modvis
Classifier: Development Status :: 2 - Pre-Alpha
Classifier: Intended Audience :: Developers
Classifier: License :: OSI Approved :: MIT License
Classifier: Natural Language :: English
Classifier: Programming Language :: Python :: 3
Classifier: Programming Language :: Python :: 3.7
Classifier: Programming Language :: Python :: 3.8
Classifier: Programming Language :: Python :: 3.9
Requires-Python: >=3.7
License-File: LICENSE
